rustoml-0.13.0.dist-info/METADATA
rustoml-0.13.0.dist-info/WHEEL
rustoml-0.13.0.dist-info/licenses/LICENSE
rustoml/__init__.py
rustoml/_rustoml.cpython-311-s390x-linux-gnu.so
rustoml/_rustoml.pyi
rustoml/py.typed
rustoml-0.13.0.dist-info/RECORD
